latex_generator_skryzhankov.py
latex_generator_skryzhankov-0.1.0.dist-info/METADATA
latex_generator_skryzhankov-0.1.0.dist-info/WHEEL
latex_generator_skryzhankov-0.1.0.dist-info/RECORD
